wheel_inspect/__init__.py
wheel_inspect/__main__.py
wheel_inspect/classes.py
wheel_inspect/errors.py
wheel_inspect/inspecting.py
wheel_inspect/metadata.py
wheel_inspect/record.py
wheel_inspect/schema.py
wheel_inspect/util.py
wheel_inspect/wheel_info.py
wheel_inspect-1.8.0.dist-info/METADATA
wheel_inspect-1.8.0.dist-info/WHEEL
wheel_inspect-1.8.0.dist-info/entry_points.txt
wheel_inspect-1.8.0.dist-info/licenses/LICENSE
wheel_inspect-1.8.0.dist-info/RECORD
