Metadata-Version: 2.4
Name: wheel-inspect
Version: 1.8.0
Summary: Extract information from wheels
Project-URL: Source Code, https://github.com/wheelodex/wheel-inspect
Project-URL: Bug Tracker, https://github.com/wheelodex/wheel-inspect/issues
Author-email: John Thorvald Wodder II <wheel-inspect@varonathe.org>
License-Expression: MIT
License-File: LICENSE
Keywords: *.dist-info,dist-info,package metadata,packages,pep427,wheel
Classifier: Intended Audience :: Developers
Classifier: Programming Language :: Python :: 3
Classifier: Programming Language :: Python :: 3 :: Only
Classifier: Programming Language :: Python :: 3.10
Classifier: Programming Language :: Python :: 3.11
Classifier: Programming Language :: Python :: 3.12
Classifier: Programming Language :: Python :: 3.13
Classifier: Programming Language :: Python :: 3.14
Classifier: Programming Language :: Python :: Implementation :: CPython
Classifier: Programming Language :: Python :: Implementation :: PyPy
Classifier: Topic :: Software Development :: Libraries :: Python Modules
Classifier: Topic :: System :: Software Distribution
Requires-Python: ~=3.10
Requires-Dist: attrs>=18.1
Requires-Dist: entry-points-txt~=0.2
Requires-Dist: headerparser<0.6,>=0.4
Requires-Dist: packaging>=17.1
Requires-Dist: readme-renderer>=24.0
Requires-Dist: wheel-filename~=2.0
